jup2py/__init__.py
jup2py/jup2pylib.py
jup2py-0.1.dev1.dist-info/LICENSE
jup2py-0.1.dev1.dist-info/METADATA
jup2py-0.1.dev1.dist-info/WHEEL
jup2py-0.1.dev1.dist-info/entry_points.txt
jup2py-0.1.dev1.dist-info/top_level.txt
jup2py-0.1.dev1.dist-info/RECORD
