Metadata-Version: 2.1
Name: jup2py
Version: 0.1.dev1
Summary: Convert jupyter notebook to .py file
Home-page: https://github.com/shivam-kotwalia/jup2py
Author: Shivam Kotwalia
Author-email: shivamkotwalia@gmail.com
License: MIT License
Keywords: Convert jupyter notebook to .py
Platform: UNKNOWN
Classifier: Programming Language :: Python :: 3.6
Classifier: Development Status :: 1 - Planning
Classifier: Operating System :: OS Independent
Classifier: License :: OSI Approved :: MIT License
Requires-Python: >3.6,!=3.3.*
Requires-Dist: nbconvert (==5.5.0)
